yescaptcha/__init__.py
yescaptcha/__version__.py
yescaptcha/client.py
yescaptcha/exceptions.py
yescaptcha/job.py
yescaptcha/settings.py
yescaptcha/task/__init__.py
yescaptcha/task/base.py
yescaptcha/task/hcaptcha_classification.py
yescaptcha/task/hcaptcha_task_proxyless.py
yescaptcha/task/image_to_text_task.py
yescaptcha/task/no_captcha_task_proxyless.py
yescaptcha/task/re_captcha_v2_classification.py
yescaptcha/task/recaptcha_v2_enterprise_task_proxyless.py
yescaptcha/task/recaptcha_v3_enterprise_task.py
yescaptcha/task/recaptcha_v3_task_proxyless.py
yescaptcha-0.1.0.dist-info/METADATA
yescaptcha-0.1.0.dist-info/WHEEL
yescaptcha-0.1.0.dist-info/top_level.txt
yescaptcha-0.1.0.dist-info/RECORD
